[
  { "id": 201, "name": "弹射", "type": "projectile", "attack": 18, "cd": 1.05, "range": 560, "speed": 720, "radius": 28, "targetRule": "nearest", "effectId": 0, "color": "#ff8c45", "projectileAnimKey": "projectile_tomato_spin", "hitAnimKey": "hit_tomato_burst" },
  { "id": 202, "name": "强力弹射", "type": "projectile", "attack": 30, "cd": 0.95, "range": 590, "speed": 760, "radius": 32, "targetRule": "nearest", "effectId": 0, "color": "#45b7ff", "projectileAnimKey": "projectile_tomato_spin", "hitAnimKey": "hit_tomato_burst" },
  { "id": 203, "name": "史诗弹射", "type": "projectile", "attack": 48, "cd": 0.8, "range": 630, "speed": 820, "radius": 36, "targetRule": "nearest", "effectId": 0, "color": "#a865ff", "projectileAnimKey": "projectile_tomato_spin", "hitAnimKey": "hit_tomato_burst" },
  { "id": 211, "name": "横扫", "type": "melee", "attack": 28, "cd": 1.45, "range": 260, "speed": 700, "radius": 78, "targetRule": "nearest", "effectId": 0, "color": "#a96b45", "projectileAnimKey": "projectile_carrot_spin", "hitAnimKey": "hit_carrot_split", "impactSpinTurns": -2, "impactSpinDuration": 0.39 },
  { "id": 212, "name": "强力横扫", "type": "melee", "attack": 42, "cd": 1.25, "range": 280, "speed": 740, "radius": 92, "targetRule": "nearest", "effectId": 0, "color": "#45b7ff", "projectileAnimKey": "projectile_carrot_spin", "hitAnimKey": "hit_carrot_split", "impactSpinTurns": -2, "impactSpinDuration": 0.39 },
  { "id": 213, "name": "史诗横扫", "type": "melee", "attack": 68, "cd": 1.05, "range": 300, "speed": 780, "radius": 108, "targetRule": "nearest", "effectId": 0, "color": "#a865ff", "projectileAnimKey": "projectile_carrot_spin", "hitAnimKey": "hit_carrot_split", "impactSpinTurns": -2, "impactSpinDuration": 0.39 },
  { "id": 221, "name": "穿刺", "type": "projectile", "attack": 24, "cd": 1.25, "range": 640, "speed": 850, "radius": 20, "targetRule": "lowestY", "effectId": 0, "color": "#71d7ff", "projectileAnimKey": "projectile_tomato_spin", "hitAnimKey": "hit_tomato_burst" },
  { "id": 222, "name": "强力穿刺", "type": "projectile", "attack": 38, "cd": 1.1, "range": 680, "speed": 900, "radius": 24, "targetRule": "lowestY", "effectId": 0, "color": "#45b7ff", "projectileAnimKey": "projectile_tomato_spin", "hitAnimKey": "hit_tomato_burst" },
  { "id": 223, "name": "史诗穿刺", "type": "projectile", "attack": 62, "cd": 0.95, "range": 720, "speed": 960, "radius": 28, "targetRule": "lowestY", "effectId": 0, "color": "#a865ff", "projectileAnimKey": "projectile_tomato_spin", "hitAnimKey": "hit_tomato_burst" },
  { "id": 231, "name": "加固", "type": "shield", "attack": 0, "cd": 4.8, "range": 0, "speed": 0, "radius": 0, "targetRule": "self", "effectId": 301, "color": "#7ee08a" },
  { "id": 232, "name": "强力加固", "type": "shield", "attack": 0, "cd": 4.2, "range": 0, "speed": 0, "radius": 0, "targetRule": "self", "effectId": 302, "color": "#45b7ff" },
  { "id": 233, "name": "史诗加固", "type": "heal", "attack": 0, "cd": 3.8, "range": 0, "speed": 0, "radius": 0, "targetRule": "self", "effectId": 303, "color": "#a865ff" },
  { "id": 241, "name": "爆裂", "type": "aoe", "attack": 36, "cd": 2.25, "range": 560, "speed": 680, "radius": 94, "targetRule": "cluster", "effectId": 0, "color": "#ffcf4a", "projectileAnimKey": "projectile_tomato_spin", "hitAnimKey": "hit_tomato_burst" },
  { "id": 242, "name": "强力爆裂", "type": "aoe", "attack": 54, "cd": 2.0, "range": 600, "speed": 720, "radius": 110, "targetRule": "cluster", "effectId": 0, "color": "#45b7ff", "projectileAnimKey": "projectile_tomato_spin", "hitAnimKey": "hit_tomato_burst" },
  { "id": 243, "name": "史诗爆裂", "type": "aoe", "attack": 82, "cd": 1.75, "range": 640, "speed": 760, "radius": 126, "targetRule": "cluster", "effectId": 0, "color": "#a865ff", "projectileAnimKey": "projectile_tomato_spin", "hitAnimKey": "hit_tomato_burst" },
  { "id": 251, "name": "毒雾", "type": "dot", "attack": 14, "cd": 2.4, "range": 540, "speed": 700, "radius": 120, "targetRule": "cluster", "effectId": 311, "color": "#7cff6b", "projectileAnimKey": "projectile_tomato_spin", "hitAnimKey": "hit_tomato_burst" },
  { "id": 252, "name": "史诗毒雾", "type": "dot", "attack": 22, "cd": 2.05, "range": 600, "speed": 760, "radius": 140, "targetRule": "cluster", "effectId": 312, "color": "#a865ff", "projectileAnimKey": "projectile_tomato_spin", "hitAnimKey": "hit_tomato_burst" }
]
